samplemono-0.1.0.dist-info/METADATA
samplemono-0.1.0.dist-info/WHEEL
samplemono/__init__.py
samplemono/samplemono.cpython-313-darwin.so
samplemono-0.1.0.dist-info/RECORD
