Metadata-Version: 2.4
Name: samplemono
Version: 0.1.0
Classifier: Programming Language :: Rust
Classifier: Programming Language :: Python :: Implementation :: CPython
Classifier: Programming Language :: Python :: Implementation :: PyPy
Summary: Open extrapolative generation with denoising
License: CC0-1.0
Requires-Python: >=3.8
